{
    "version": "0.6.1",
    "description": "A cross-platform command-line tool for executing jobs in parallel",
    "homepage": "https://github.com/shenwei356/rush",
    "license": "MIT",
    "architecture": {
        "64bit": {
            "url": "https://github.com/shenwei356/rush/releases/download/v0.6.1/rush_windows_amd64.exe.tar.gz",
            "hash": "1e548ce0cc894d067a371a59c53d2e0c97cb4dae8879c13f3762ec1eb5a66a82"
        },
        "32bit": {
            "url": "https://github.com/shenwei356/rush/releases/download/v0.6.1/rush_windows_386.exe.tar.gz",
            "hash": "9c76eefedab7634ba377b471f0c73d8dd9cc675309c6e9de7364047e6c750ee8"
        }
    },
    "bin": "rush.exe",
    "checkver": "github",
    "autoupdate": {
        "architecture": {
            "64bit": {
                "url": "https://github.com/shenwei356/rush/releases/download/v$version/rush_windows_amd64.exe.tar.gz"
            },
            "32bit": {
                "url": "https://github.com/shenwei356/rush/releases/download/v$version/rush_windows_386.exe.tar.gz"
            }
        }
    }
}
