{
    "version": "1.554.0",
    "description": "A CLI tool for interacting with the Speakeasy platform and its API",
    "homepage": "https://speakeasy.com",
    "license": "Elastic-2.0",
    "architecture": {
        "64bit": {
            "url": "https://github.com/speakeasy-api/speakeasy/releases/download/v1.554.0/speakeasy_windows_amd64.zip",
            "hash": "a1d1cdd73d7133e81e32558b8aef87b3dbd18e3349f0019526365df79f30e497"
        },
        "32bit": {
            "url": "https://github.com/speakeasy-api/speakeasy/releases/download/v1.554.0/speakeasy_windows_386.zip",
            "hash": "6cb13d03827830473ac165c5abce13057eeb4f4a8e393bf39458bf79d628d801"
        },
        "arm64": {
            "url": "https://github.com/speakeasy-api/speakeasy/releases/download/v1.554.0/speakeasy_windows_arm64.zip",
            "hash": "4ac4049a245f4067b90ea30cc7820764705b327d55017ae1f488f1777f68255e"
        }
    },
    "bin": "speakeasy.exe",
    "checkver": {
        "github": "https://github.com/speakeasy-api/speakeasy"
    },
    "autoupdate": {
        "architecture": {
            "64bit": {
                "url": "https://github.com/speakeasy-api/speakeasy/releases/download/v$version/speakeasy_windows_amd64.zip"
            },
            "32bit": {
                "url": "https://github.com/speakeasy-api/speakeasy/releases/download/v$version/speakeasy_windows_386.zip"
            },
            "arm64": {
                "url": "https://github.com/speakeasy-api/speakeasy/releases/download/v$version/speakeasy_windows_arm64.zip"
            }
        },
        "hash": {
            "url": "$baseurl/checksums.txt"
        }
    }
}
