{
    "version": "2022.12.27.810",
    "description": "Daily builds of yt-dlp by github.com/ytdl-patched. Do not request support for these builds.",
    "homepage": "https://github.com/ytdl-patched/yt-dlp",
    "license": "Unlicense",
    "suggest": {
        "ffmpeg": [
            "scoop-alts/ffmpeg-shared-nightly",
            "ffmpeg-yt-dlp",
            "ffmpeg"
        ]
    },
    "architecture": {
        "64bit": {
            "url": "https://github.com/ytdl-patched/yt-dlp/releases/download/2022.12.27.810/yt-dlp.exe",
            "hash": "sha512:5f7f4b11210864cb6aee60e1118255359a1e1721b44f8f346e7b2d1fdd763cb29fc85d8125bd00622bf60097098a148efab013bd6d273d3462e50e9a11675535"
        },
        "32bit": {
            "url": "https://github.com/ytdl-patched/yt-dlp/releases/download/2022.12.27.810/yt-dlp_x86.exe#/yt-dlp.exe",
            "hash": "sha512:23253a89da767e40c2098ab61f0cd7ef09b343edb90359e162ed9bccecb156d051084d3a4e5554a3cfa120674ef4688e07b7a3f8ad44a512b6a358b12ec1117d"
        }
    },
    "bin": "yt-dlp.exe",
    "pre_install": "if (-not (Test-Path \"$persist_dir\\yt-dlp.conf\")) { New-Item \"$dir\\yt-dlp.conf\" -ItemType file | Out-Null }",
    "persist": [
        "yt-dlp.conf",
        "ytdlp_plugins"
    ],
    "checkver": "github",
    "autoupdate": {
        "architecture": {
            "64bit": {
                "url": "https://github.com/ytdl-patched/yt-dlp/releases/download/$version/yt-dlp.exe"
            },
            "32bit": {
                "url": "https://github.com/ytdl-patched/yt-dlp/releases/download/$version/yt-dlp_x86.exe#/yt-dlp.exe"
            }
        },
        "hash": {
            "url": "$baseurl/SHA2-512SUMS"
        }
    }
}
